README
setup.py
rapy/__init__.py
rapy/csp.py
rapy/cspnvm.py
rapy/font.py
rapy/ftdi.py
rapy/ftdi_i2c.py
rapy/i2c.py
rapy/isp.py
rapy/py_writer.csh
rapy/sh1106.py
rapy.egg-info/PKG-INFO
rapy.egg-info/SOURCES.txt
rapy.egg-info/dependency_links.txt
rapy.egg-info/not-zip-safe
rapy.egg-info/top_level.txt