Metadata-Version: 1.1
Name: rapy
Version: 0.101
Summary: Ray's private DVT utilities
Home-page: http://canyon-semi.com.tw
Author: Ray Huang
Author-email: rayjhuang@msn.com
License: UNKNOWN
Platform: UNKNOWN
Classifier: Development Status :: 3 - Alpha
Classifier: Framework :: IDLE
Classifier: Intended Audience :: Developers
Classifier: License :: OSI Approved :: MIT License
Classifier: Natural Language :: English
Classifier: Operating System :: Microsoft :: Windows :: Windows 7
Classifier: Operating System :: MacOS :: MacOS X
Classifier: Programming Language :: Python :: 2.7
Classifier: Topic :: Utilities
